vasp_suite/__init__.py
vasp_suite/__version__.py
vasp_suite/cli.py
vasp_suite/conv.py
vasp_suite/core.py
vasp_suite/graphs.py
vasp_suite/hessian.py
vasp_suite/input.py
vasp_suite/parser.py
vasp_suite/phonon.py
vasp_suite/structure.py
vasp_suite/submission.py
vasp_suite-1.14.0.dist-info/licenses/LICENSE
vasp_suite-1.14.0.dist-info/METADATA
vasp_suite-1.14.0.dist-info/WHEEL
vasp_suite-1.14.0.dist-info/entry_points.txt
vasp_suite-1.14.0.dist-info/top_level.txt
vasp_suite-1.14.0.dist-info/RECORD
