Metadata-Version: 2.4
Name: vasp_suite
Version: 1.14.0
Summary: A package for creating and handling input files for vasp
Author: Chilton Group
Author-email: nicholas.chilton@manchester.ac.uk
Classifier: Programming Language :: Python :: 3
Classifier: License :: OSI Approved :: GNU General Public License v3 (GPLv3)
Classifier: Operating System :: OS Independent
Requires-Python: >=3.6
License-File: LICENSE
Requires-Dist: numpy
Requires-Dist: gemmi
Requires-Dist: matplotlib
Requires-Dist: scipy
Requires-Dist: ase
Requires-Dist: spglib
Requires-Dist: seekpath
Dynamic: author
Dynamic: author-email
Dynamic: classifier
Dynamic: description
Dynamic: description-content-type
Dynamic: license-file
Dynamic: requires-dist
Dynamic: requires-python
Dynamic: summary
